Metadata-Version: 1.1
Name: xtas
Version: 3.4
Summary: Distributed text analysis suite
Home-page: https://github.com/NLeSC/xtas
Author: Lars Buitinck
Author-email: l.buitinck@esciencecenter.nl
License: UNKNOWN
Platform: UNKNOWN
Classifier: Intended Audience :: Science/Research
Classifier: License :: OSI Approved :: Apache Software License
Classifier: Topic :: Scientific/Engineering
Classifier: Topic :: Scientific/Engineering :: Information Analysis
Classifier: Topic :: Text Processing
